eth_tester_client/__init__.py
eth_tester_client/client.py
eth_tester_client/filters.py
eth_tester_client/serializers.py
eth_tester_client/utils.py
ethereum_tester_client-1.2.5.dist-info/DESCRIPTION.rst
ethereum_tester_client-1.2.5.dist-info/METADATA
ethereum_tester_client-1.2.5.dist-info/RECORD
ethereum_tester_client-1.2.5.dist-info/WHEEL
ethereum_tester_client-1.2.5.dist-info/metadata.json
ethereum_tester_client-1.2.5.dist-info/top_level.txt
