Metadata-Version: 2.0
Name: ethereum-tester-client
Version: 1.2.5
Summary: Ethereum JSON RPC Client for testing
Home-page: https://github.com/pipermerriam/ethereum-tester-client
Author: Piper Merriam
Author-email: pipermerriam@gmail.com
License: MIT
Keywords: ethereum
Platform: UNKNOWN
Classifier: Development Status :: 2 - Pre-Alpha
Classifier: Intended Audience :: Developers
Classifier: License :: OSI Approved :: BSD License
Classifier: Natural Language :: English
Classifier: Programming Language :: Python :: 2
Classifier: Programming Language :: Python :: 2.7
Classifier: Programming Language :: Python :: 3
Classifier: Programming Language :: Python :: 3.4
Classifier: Programming Language :: Python :: 3.5
Requires-Dist: ethereum (>=1.5.2)
Requires-Dist: gevent (>=1.1.2)
